monze/__init__.py
monze/beheer.py
monze/dnd.py
monze/editviews.py
monze/emails.py
monze/general.py
monze/groepen.py
monze/home.py
monze/jinja_filters.py
monze/move.py
monze/singletons.py
monze/startup.html
monze/studenten.py
monze/views.py
monze/website.py
monze/static/base.css
monze/static/beheer.css
monze/static/beheer.js
monze/static/codelogo.png
monze/static/cpnits-picto.ico
monze/static/cpnits-picto.png
monze/static/dnd.css
monze/static/global.js
monze/static/home.css
monze/static/jquery-371.js
monze/static/jquery-confirm.css
monze/static/jquery-confirm.js
monze/static/jquery-ui.css
monze/static/jquery-ui.js
monze/static/jquery-ui.structure.css
monze/static/jquery-ui.theme.css
monze/static/roboto-mono-v23-latin-100.woff2
monze/static/roboto-mono-v23-latin-200.woff2
monze/static/roboto-mono-v23-latin-300.woff2
monze/static/roboto-mono-v23-latin-500.woff2
monze/static/roboto-mono-v23-latin-600.woff2
monze/static/roboto-mono-v23-latin-700.woff2
monze/static/roboto-mono-v23-latin-regular.woff2
monze/static/studenten.css
monze/static/views.css
monze/static/website.css
monze/static/website.js
monze/templates/404.html
monze/templates/_head.html
monze/templates/_menu.html
monze/templates/beheer.html
monze/templates/editviews.html
monze/templates/email-single.html
monze/templates/groep-studenten.html
monze/templates/home.html
monze/templates/login.html
monze/templates/move.html
monze/templates/student.html
monze/templates/studenten-import.html
monze/templates/studenten.html
monze/templates/studenten.js
monze/templates/view-studenten.html
monze/templates/website.html
monze-1.0.21.dist-info/licenses/LICENSE
monze-1.0.21.dist-info/METADATA
monze-1.0.21.dist-info/WHEEL
monze-1.0.21.dist-info/entry_points.txt
monze-1.0.21.dist-info/top_level.txt
monze-1.0.21.dist-info/RECORD
