Metadata-Version: 2.4
Name: monze
Version: 1.0.21
Summary: Monze is the new Butterfly
Author-email: "Victor G.B. Peters" <victor@jeex.eu>
Project-URL: Homepage, https://github.com/jeex/monze
Project-URL: Issues, https://github.com/jeex/monze/issues
Classifier: Programming Language :: Python :: 3
Classifier: License :: OSI Approved :: MIT License
Classifier: Operating System :: OS Independent
Requires-Python: >=3.11
License-File: LICENSE
Requires-Dist: PyYAML
Requires-Dist: Flask
Requires-Dist: bleach
Requires-Dist: pytz
Requires-Dist: appdirs
Requires-Dist: colorama
Requires-Dist: requests
Requires-Dist: pymongo
Requires-Dist: unidecode
Requires-Dist: pylightxl
Requires-Dist: validators
Requires-Dist: pyqt6
Requires-Dist: screeninfo
Dynamic: license-file
